{
  "type": "entity",
  "name": "Saint-Paul",
  "order": "1",
  "id": "1",
  "sub-type": {
    "type": "contents",
    "name": "patients",
    "order": "2",
    "id": "1",
    "sub-type": {
      "type": "column",
      "name": "patient",
      "order": "3",
      "id": "1",
      "sub-type": [
        {
          "type": "element",
          "name": "patient-information",
          "order": "4",
          "firstname": "Minji KIM",
          "age": 19,
          "city": "Seoul",
          "status": "booking confirmed"
        },
        {
          "type": "element",
          "name": "patient-information",
          "order": "4",
          "firstname": "Hyerin KANG ",
          "age": 17,
          "city": "Seoul",
          "status": "booking confirmed"
        },
        {
          "type": "element",
          "name": "patient-information",
          "order": "4",
          "firstname": "Hanni DANIELLE PAM",
          "age": 19,
          "city": "Seoul",
          "status": "booking confirmed"
        },
        {
          "type": "element",
          "name": "patient-information",
          "order": "4",
          "firstname": "Hyein JULIEN MICHELLE TEST",
          "age": 19,
          "city": "Seoul",
          "status": "canceled"
        },
        {
          "type": "element",
          "name": "patient-information",
          "order": "4",
          "firstname": "Danielle PIERRE LOPEZ",
          "age": 19,
          "city": "Seoul",
          "status": "booking confirmed"
        }
      ]
    }
  }
}
